fastapi_casdoor/__init__.py
fastapi_casdoor/context.py
fastapi_casdoor/deps.py
fastapi_casdoor/init.py
fastapi_casdoor/models.py
fastapi_casdoor/router.py
fastapi_casdoor/settings.py
fastapi_casdoor/utils.py
fastapi_casdoor/validators.py
fastapi_casdoor-0.1.10.dist-info/LICENSE
fastapi_casdoor-0.1.10.dist-info/METADATA
fastapi_casdoor-0.1.10.dist-info/WHEEL
fastapi_casdoor-0.1.10.dist-info/top_level.txt
fastapi_casdoor-0.1.10.dist-info/RECORD
